bloom/__init__.py
bloom/config.py
bloom/git.py
bloom/github.py
bloom/logging.py
bloom/packages.py
bloom/rosdistro_api.py
bloom/summary.py
bloom/util.py
bloom/commands/__init__.py
bloom/commands/export_upstream.py
bloom/commands/generate.py
bloom/commands/release.py
bloom/commands/update.py
bloom/commands/git/__init__.py
bloom/commands/git/branch.py
bloom/commands/git/config.py
bloom/commands/git/generate.py
bloom/commands/git/import_upstream.py
bloom/commands/git/release.py
bloom/commands/git/patch/__init__.py
bloom/commands/git/patch/common.py
bloom/commands/git/patch/export_cmd.py
bloom/commands/git/patch/import_cmd.py
bloom/commands/git/patch/patch_main.py
bloom/commands/git/patch/rebase_cmd.py
bloom/commands/git/patch/remove_cmd.py
bloom/commands/git/patch/trim_cmd.py
bloom/generators/__init__.py
bloom/generators/common.py
bloom/generators/release.py
bloom/generators/rosdebian.py
bloom/generators/rosrelease.py
bloom/generators/rosrpm.py
bloom/generators/debian/__init__.py
bloom/generators/debian/generate_cmd.py
bloom/generators/debian/generator.py
bloom/generators/debian/templates/ament_cmake/changelog.em
bloom/generators/debian/templates/ament_cmake/compat.em
bloom/generators/debian/templates/ament_cmake/control.em
bloom/generators/debian/templates/ament_cmake/copyright.em
bloom/generators/debian/templates/ament_cmake/gbp.conf.em
bloom/generators/debian/templates/ament_cmake/rules.em
bloom/generators/debian/templates/ament_cmake/source/format.em
bloom/generators/debian/templates/ament_cmake/source/options.em
bloom/generators/debian/templates/ament_python/changelog.em
bloom/generators/debian/templates/ament_python/compat.em
bloom/generators/debian/templates/ament_python/control.em
bloom/generators/debian/templates/ament_python/copyright.em
bloom/generators/debian/templates/ament_python/gbp.conf.em
bloom/generators/debian/templates/ament_python/rules.em
bloom/generators/debian/templates/ament_python/source/format.em
bloom-0.13.0.dist-info/LICENSE.txt
bloom-0.13.0.dist-info/METADATA
bloom-0.13.0.dist-info/WHEEL
bloom-0.13.0.dist-info/entry_points.txt
bloom-0.13.0.dist-info/top_level.txt
bloom-0.13.0.dist-info/RECORD
