Metadata-Version: 2.1
Name: bloom
Version: 0.13.0
Summary: Bloom is a release automation tool.
Home-page: http://www.ros.org/wiki/bloom
Author: Tully Foote, William Woodall
Author-email: tfoote@openrobotics.org, william@openrobotics.org
Maintainer: William Woodall
Maintainer-email: william@openrobotics.org
License: BSD
Keywords: ROS
Platform: UNKNOWN
Classifier: Programming Language :: Python
Classifier: License :: OSI Approved :: BSD License
Requires-Dist: PyYAML
Requires-Dist: catkin-pkg (>=0.4.3)
Requires-Dist: empy (<4)
Requires-Dist: packaging
Requires-Dist: python-dateutil
Requires-Dist: rosdep (>=0.15.0)
Requires-Dist: rosdistro (>=0.8.0)
Requires-Dist: setuptools
Requires-Dist: vcstools (>=0.1.22)
Provides-Extra: test
Requires-Dist: pep8 ; extra == 'test'
Requires-Dist: pytest ; extra == 'test'
